torchlings/__init__.py
torchlings/cli.py
torchlings/pretty.py
torchlings/runner.py
torchlings/utils.py
torchlings/venv.py
torchlings/exercises/exercise.py
torchlings/exercises/01_tensors/1.py
torchlings/exercises/01_tensors/2.py
torchlings/exercises/01_tensors/3.py
torchlings/exercises/01_tensors/4.py
torchlings/exercises/01_tensors/5.py
torchlings/exercises/01_tensors/6.py
torchlings/exercises/01_tensors/7.py
torchlings/exercises/02_autograd/1.py
torchlings/exercises/02_autograd/2.py
torchlings/exercises/02_autograd/3.py
torchlings/exercises/02_autograd/4.py
torchlings/exercises/02_autograd/5.py
torchlings-0.1.20.dist-info/METADATA
torchlings-0.1.20.dist-info/WHEEL
torchlings-0.1.20.dist-info/entry_points.txt
torchlings-0.1.20.dist-info/top_level.txt
torchlings-0.1.20.dist-info/RECORD
